.travis.yml
CHANGES.rst
MANIFEST.in
README.rst
buildout.cfg
setup.py
versions.cfg
docs/LICENSE.GPL
docs/LICENSE.txt
src/imio/__init__.py
src/imio.amqp.egg-info/PKG-INFO
src/imio.amqp.egg-info/SOURCES.txt
src/imio.amqp.egg-info/dependency_links.txt
src/imio.amqp.egg-info/entry_points.txt
src/imio.amqp.egg-info/namespace_packages.txt
src/imio.amqp.egg-info/not-zip-safe
src/imio.amqp.egg-info/requires.txt
src/imio.amqp.egg-info/top_level.txt
src/imio/amqp/__init__.py
src/imio/amqp/base.py
src/imio/amqp/consumer.py
src/imio/amqp/dispatcher.py
src/imio/amqp/event.py
src/imio/amqp/exception.py
src/imio/amqp/publisher.py
src/imio/amqp/tests/__init__.py
src/imio/amqp/tests/base.py
src/imio/amqp/tests/test_consumer.py
src/imio/amqp/tests/test_dispatcher.py
src/imio/amqp/tests/test_publisher.py