Metadata-Version: 2.1
Name: imio.amqp
Version: 0.3.0
Summary: UNKNOWN
Home-page: https://github.com/imio/
Author: IMIO
Author-email: support@imio.be
License: GPL
Platform: UNKNOWN
Classifier: Programming Language :: Python
Provides-Extra: test
